{
	"data": {
		"gor":8,
		"vert":6,
		"width":150,
		"height":150,
		"backTile":"back_tiles",
		"blockTile":"tileRed",
		"sector_name":"sector",
		"tex_mask_pref":"_mask",
		"pipe_coner":{
			"w":112,
			"h":112
		},
		"pipe_line":{
			"w":150,
			"h":150
		},
		"pipe_triple":{
			"w":112,
			"h":150
		},
		"pipe_krest":{
			"w":150,
			"h":150
		},
		"pipe_start":{
			"w":150,
			"h":150
		},
		"pipe_end":{
			"w":150,
			"h":150
		},
		"start":"sector_1_0",
		"end":"sector_5_7",
		"timer":45
	},
	"sectors":{
		"sector_0_0":{"mode":"clear", "tex":"", "rotate":0, "type":"opacity"},
		"sector_0_1":{"mode":"pipe", "tex":"pipe_coner", "rotate":1.5,"type":"active"},
		"sector_0_2":{"mode":"pipe", "tex":"pipe_line", "rotate":0.0, "type":"active"},
		"sector_0_3":{"mode":"pipe", "tex":"pipe_triple", "rotate":1.0, "type":"active"},
		"sector_0_4":{"mode":"pipe", "tex":"pipe_coner", "rotate":1.0,"type":"active"},
		"sector_0_5":{"mode":"pipe", "tex":"pipe_line", "rotate":0.5, "type":"active"},
		"sector_0_6":{"mode":"pipe", "tex":"pipe_coner", "rotate":0.5,"type":"active"},
		"sector_0_7":{"mode":"clear", "tex":"", "rotate":0, "type":"opacity"},
		
		"sector_1_0":{"mode":"pipe", "tex":"pipe_start", "rotate":0.5, "type":"opacity"},
		"sector_1_1":{"mode":"pipe", "tex":"pipe_triple", "rotate":1.0, "type":"active"},
		"sector_1_2":{"mode":"pipe", "tex":"pipe_coner", "rotate":0.0, "type":"active"},
		"sector_1_3":{"mode":"pipe", "tex":"pipe_line", "rotate":0.0,"type":"active"},
		"sector_1_4":{"mode":"pipe", "tex":"pipe_line", "rotate":0.5, "type":"active"},
		"sector_1_5":{"mode":"pipe", "tex":"pipe_krest", "rotate":0.0, "type":"active"},
		"sector_1_6":{"mode":"pipe", "tex":"pipe_coner", "rotate":0.0, "type":"active"},
		"sector_1_7":{"mode":"clear", "tex":"", "rotate":0, "type":"opacity"},
		
		"sector_2_0":{"mode":"clear", "tex":"", "rotate":0, "type":"opacity"},
		"sector_2_1":{"mode":"pipe", "tex":"pipe_line", "rotate":0.5,"type":"active"},
		"sector_2_2":{"mode":"pipe", "tex":"pipe_coner", "rotate":0.0, "type":"active"},
		"sector_2_3":{"mode":"pipe", "tex":"pipe_coner", "rotate": 0.0,	"type":"active"},
		"sector_2_4":{"mode":"pipe", "tex":"pipe_triple", "rotate":0.5,"type":"active"},	
		"sector_2_5":{"mode":"pipe", "tex":"pipe_line","rotate":0.0,"type":"active"},
		"sector_2_6":{"mode":"pipe", "tex":"pipe_line","rotate":0.5,"type":"active"},
		"sector_2_7":{"mode":"clear", "tex":"", "rotate":0, "type":"opacity"},
	

		"sector_3_0":{"mode":"clear", "tex":"", "rotate":0, "type":"opacity"},
		"sector_3_1":{"mode":"pipe", "tex":"pipe_coner", "rotate":1.0,"type":"active"},
		"sector_3_2":{"mode":"pipe", "tex":"pipe_krest", "rotate":0.0, "type":"active"},
		"sector_3_3":{"mode":"pipe", "tex":"pipe_line", "rotate": 0.5,	"type":"active"},
		"sector_3_4":{"mode":"pipe", "tex":"pipe_coner", "rotate":0.5,"type":"active"},	
		"sector_3_5":{"mode":"pipe", "tex":"pipe_coner","rotate":0.0,"type":"active"},
		"sector_3_6":{"mode":"pipe", "tex":"pipe_line","rotate":0.0,"type":"active"},
		"sector_3_7":{"mode":"clear", "tex":"", "rotate":0, "type":"opacity"},	
		
		"sector_4_0":{"mode":"clear", "tex":"", "rotate":0, "type":"opacity"},
		"sector_4_1":{"mode":"pipe", "tex":"pipe_coner", "rotate":0.0,"type":"active"},
		"sector_4_2":{"mode":"pipe", "tex":"pipe_line", "rotate":0.0, "type":"active"},
		"sector_4_3":{"mode":"pipe", "tex":"pipe_coner", "rotate": 1.0,	"type":"active"},
		"sector_4_4":{"mode":"pipe", "tex":"pipe_triple", "rotate":0.0,"type":"active"},	
		"sector_4_5":{"mode":"pipe", "tex":"pipe_line","rotate":0.5,"type":"active"},
		"sector_4_6":{"mode":"pipe", "tex":"pipe_line","rotate":0.5,"type":"active"},
		"sector_4_7":{"mode":"clear", "tex":"", "rotate":0, "type":"opacity"},	

		"sector_5_0":{"mode":"clear", "tex":"", "rotate":0, "type":"opacity"},
		"sector_5_1":{"mode":"pipe", "tex":"pipe_triple", "rotate":1.0,"type":"active"},
		"sector_5_2":{"mode":"pipe", "tex":"pipe_coner", "rotate":0.0, "type":"active"},
		"sector_5_3":{"mode":"pipe", "tex":"pipe_coner", "rotate": 1.0,	"type":"active"},
		"sector_5_4":{"mode":"pipe", "tex":"pipe_coner", "rotate":1.0,"type":"active"},	
		"sector_5_5":{"mode":"pipe", "tex":"pipe_triple","rotate":0.0,"type":"active"},
		"sector_5_6":{"mode":"pipe", "tex":"pipe_coner","rotate":1.0,"type":"active"},
		"sector_5_7":{"mode":"pipe", "tex":"pipe_end", "rotate": 1.5, "type":"opacity"},
		
		"sector_6_0":{"mode":"clear", "tex":"", "rotate":0, "type":"opacity"},
		"sector_6_1":{"mode":"pipe", "tex":"pipe_krest", "rotate":0.0,"type":"active"},
		"sector_6_2":{"mode":"pipe", "tex":"pipe_line", "rotate":0.5, "type":"active"},
		"sector_6_3":{"mode":"pipe", "tex":"pipe_line", "rotate": 0.0,	"type":"active"},
		"sector_6_4":{"mode":"pipe", "tex":"pipe_coner", "rotate":0.0,"type":"active"},	
		"sector_6_5":{"mode":"pipe", "tex":"pipe_krest","rotate":0.0,"type":"active"},
		"sector_6_6":{"mode":"pipe", "tex":"pipe_coner","rotate":0.0,"type":"active"},
		"sector_6_7":{"mode":"clear", "tex":"", "rotate":0, "type":"opacity"}
	}	
}
